image_transform_rgbgray/__init__.py
image_transform_rgbgray/processing/__init__.py
image_transform_rgbgray/processing/transformation.py
image_transform_rgbgray/utils/__init__.py
image_transform_rgbgray/utils/io.py
transform_rgbgray-0.0.1.dist-info/METADATA
transform_rgbgray-0.0.1.dist-info/WHEEL
transform_rgbgray-0.0.1.dist-info/top_level.txt
transform_rgbgray-0.0.1.dist-info/RECORD
