Metadata-Version: 2.1
Name: transform-rgbgray
Version: 0.0.1
Summary: Pacote de transformação de imagens
Home-page: https://github.com/JorgeMagno/image-processing-image-python
Author: Jorge Magno
Author-email: jorge.magnolm@gmail.com
License: UNKNOWN
Platform: UNKNOWN
Requires-Python: >=3.8
